irreptables/__convertTab.py
irreptables/__init__.py
irreptables/tables/irreps-SG=1-scal.dat
irreptables/tables/irreps-SG=1-spin.dat
irreptables/tables/irreps-SG=10-scal.dat
irreptables/tables/irreps-SG=10-spin.dat
irreptables/tables/irreps-SG=100-scal.dat
irreptables/tables/irreps-SG=100-spin.dat
irreptables/tables/irreps-SG=101-scal.dat
irreptables/tables/irreps-SG=101-spin.dat
irreptables/tables/irreps-SG=102-scal.dat
irreptables/tables/irreps-SG=102-spin.dat
irreptables/tables/irreps-SG=103-scal.dat
irreptables/tables/irreps-SG=103-spin.dat
irreptables/tables/irreps-SG=104-scal.dat
irreptables/tables/irreps-SG=104-spin.dat
irreptables/tables/irreps-SG=105-scal.dat
irreptables/tables/irreps-SG=105-spin.dat
irreptables/tables/irreps-SG=106-scal.dat
irreptables/tables/irreps-SG=106-spin.dat
irreptables/tables/irreps-SG=107-scal.dat
irreptables/tables/irreps-SG=107-spin.dat
irreptables/tables/irreps-SG=108-scal.dat
irreptables/tables/irreps-SG=108-spin.dat
irreptables/tables/irreps-SG=109-scal.dat
irreptables/tables/irreps-SG=109-spin.dat
irreptables/tables/irreps-SG=11-scal.dat
irreptables/tables/irreps-SG=11-spin.dat
irreptables/tables/irreps-SG=110-scal.dat
irreptables/tables/irreps-SG=110-spin.dat
irreptables/tables/irreps-SG=111-scal.dat
irreptables/tables/irreps-SG=111-spin.dat
irreptables/tables/irreps-SG=112-scal.dat
irreptables/tables/irreps-SG=112-spin.dat
irreptables/tables/irreps-SG=113-scal.dat
irreptables/tables/irreps-SG=113-spin.dat
irreptables/tables/irreps-SG=114-scal.dat
irreptables/tables/irreps-SG=114-spin.dat
irreptables/tables/irreps-SG=115-scal.dat
irreptables/tables/irreps-SG=115-spin.dat
irreptables/tables/irreps-SG=116-scal.dat
irreptables/tables/irreps-SG=116-spin.dat
irreptables/tables/irreps-SG=117-scal.dat
irreptables/tables/irreps-SG=117-spin.dat
irreptables/tables/irreps-SG=118-scal.dat
irreptables/tables/irreps-SG=118-spin.dat
irreptables/tables/irreps-SG=119-scal.dat
irreptables/tables/irreps-SG=119-spin.dat
irreptables-1.1.1.dist-info/METADATA
irreptables-1.1.1.dist-info/WHEEL
irreptables-1.1.1.dist-info/top_level.txt
irreptables-1.1.1.dist-info/RECORD
