Metadata-Version: 2.1
Name: irreptables
Version: 1.1.1
Summary: Tables of characters of irreducible representations for double space groups. Part of 'irrep' package
Home-page: https://github.com/stepan-tsirkin/irrep
Author: Stepan S. Tsirkin
Author-email: stepan.tsirkin@ehu.eus
Classifier: Programming Language :: Python :: 3
Classifier: License :: OSI Approved :: GNU General Public License v3 (GPLv3)
Classifier: Operating System :: OS Independent
Requires-Dist: numpy
Requires-Dist: scipy >=1.0
Requires-Dist: spglib >=1.14
Requires-Dist: lazy-property
Requires-Dist: Click
